pyl/__init__.py
pyl/__main__.py
python_pyl-0.1.0.dist-info/METADATA
python_pyl-0.1.0.dist-info/WHEEL
python_pyl-0.1.0.dist-info/entry_points.txt
python_pyl-0.1.0.dist-info/licenses/LICENSE
python_pyl-0.1.0.dist-info/RECORD
