Metadata-Version: 2.4
Name: python-pyl
Version: 0.1.0
Summary: Python for shell scripting
Project-URL: Homepage, https://github.com/BenjyWiener/pyl
Project-URL: Repository, https://github.com/BenjyWiener/pyl
Author: Benjy Wiener
License-Expression: MIT
License-File: LICENSE
Keywords: commandline,shell
Classifier: Development Status :: 3 - Alpha
Classifier: Operating System :: OS Independent
Classifier: Programming Language :: Python :: 3
Classifier: Programming Language :: Python :: 3.12
Classifier: Programming Language :: Python :: 3.13
Classifier: Programming Language :: Python :: Implementation :: CPython
Classifier: Topic :: Software Development :: Pre-processors
Requires-Python: >=3.12
Requires-Dist: macro-polo~=0.3.0
